wandelbots/__init__.py
wandelbots/apis/__init__.py
wandelbots/apis/controller.py
wandelbots/apis/controller_io.py
wandelbots/apis/device_configuration.py
wandelbots/apis/motion.py
wandelbots/apis/motion_group.py
wandelbots/apis/motion_group_infos.py
wandelbots/core/__init__.py
wandelbots/core/instance.py
wandelbots/core/motiongroup.py
wandelbots/core/plan_result.py
wandelbots/core/planner.py
wandelbots/exceptions/__init__.py
wandelbots/exceptions/exceptions.py
wandelbots/request/__init__.py
wandelbots/request/asyncs.py
wandelbots/request/config.py
wandelbots/request/syncs.py
wandelbots/types/__init__.py
wandelbots/types/ios.py
wandelbots/types/pose.py
wandelbots/types/vector3d.py
wandelbots/util/__init__.py
wandelbots/util/logger.py
wandelbots-0.5.7.dist-info/LICENSE
wandelbots-0.5.7.dist-info/METADATA
wandelbots-0.5.7.dist-info/WHEEL
wandelbots-0.5.7.dist-info/RECORD
