Metadata-Version: 2.3
Name: wandelbots
Version: 0.5.7
Summary: Deprecated Python client for the Wandelbots API. There will be no further updates of this package. Please consider migrating to [wandelbots-nova](https://pypi.org/project/wandelbots-nova).
Author: Martin George
Author-email: martin.george@wandelbots.com
Requires-Python: >=3.9,<4.0
Classifier: Programming Language :: Python :: 3
Classifier: Programming Language :: Python :: 3.9
Classifier: Programming Language :: Python :: 3.10
Classifier: Programming Language :: Python :: 3.11
Classifier: Programming Language :: Python :: 3.12
Classifier: Programming Language :: Python :: 3.13
Requires-Dist: httpx (==0.27.2)
Requires-Dist: nbqa (>=1.9.0,<2.0.0)
Requires-Dist: numpy (>=1.26,<2.0)
Requires-Dist: requests (==2.32.3)
Requires-Dist: scipy (>=1.11,<2.0)
Requires-Dist: wandelbots_api_client (==24.8.0rc6)
Requires-Dist: websockets (>=14.0.0)
